piri/__init__.py
piri/casting.py
piri/collection_handlers.py
piri/common.py
piri/constants.py
piri/functions.py
piri/handlers.py
piri/iso.py
piri/mapper.py
piri/process.py
piri/schema.json
piri/schema.py
piri/valuetypes.py
piri-2.2.0.dist-info/LICENSE
piri-2.2.0.dist-info/WHEEL
piri-2.2.0.dist-info/METADATA
piri-2.2.0.dist-info/RECORD
